{
    "products": [
    {
    "id": 5,
    "name": "Reinforced", 
    "category": "glass",
    "price": 33.78,
    "currency": "USD", 
    "image": {
    "src": "https://inteng-storage.s3.amazonaws.com/img/iea/Xy6x9oE7wr/sizes/glass_md.jpg",
    "alt": ""
    },
    "bestseller": true, 
    "featured": false, 
    "details": null
    },
    
    {
        "id": 3,
        "name": "Shape",
        "category": "steel", 
        "price": 101,
        "currency": "USD",
        "image": "https://images.fineartamerica.com/images-medium-large-5/brushed-steel-metal-texture-2-redlightimage.jpg",
        "bestseller": false, 
        "featured": false,
        "details": null
    },

    {
        "id": 1,
        "name": "Shape",
        "category": "wood",
        "price": 93.89,
        "currency": "USD",
        "image": {
            "src": "http://geomiq.com/wp-content/uploads/2019/08/kisspng-sheet-metal-molybdenum-stainless-steel-rolling-inc-steel-plate-5aea05f508ace2.0164818015252863890355.png"
        },
        "bestseller": false, 
        "featured": false,
        "details": null
    },

    {
        "id": 2,
        "name": "Wave",
        "category": "brick",
        "price": 120.21,
        "currency": "USD", 
        "image": {
        "src": "https://ae01.alicdn.com/kf/Haf859724a1fb4969b0c14c361feafa753/Plaque-en-acier-inoxydable-1-5-paisseur-de-1mm-304mm-2mm-3mm-traitement-du-m-tal.jpg_Q90.jpg_.webp",
        "alt": ""
        },
        "bestseller": false, 
        "featured": false,
        "details": null
    },
 
    {
        "id": 9,
        "name": "Shape2",
        "category": "concrete", 
        "price": 156,
        "currency": "USD",
        "image": "https://images.fineartamerica.com/images-medium-large-5/brushed-steel-metal-texture-2-redlightimage.jpg",
        "bestseller": true, 
        "featured": false,
        "details": null
    },
      
    {
        "id": 4,
        "name": "Recycled Plastic", 
        "category": "plastic",
        "price": 101,
        "currency": "USD", 
        "image": {
        "src": "https://everytexture.com/wp-content/uploads/2018/10/everytexture.com-stock-plastic-texture-00022-1024x768.jpg",
        "alt": ""
        },
        "bestseller": false, 
        "featured": true,
        "details": {
        "weight": 2340,
        "thickness": 2,
        "description": "",
        "recommendations": [
        {
            "src": "https://static1.bigstockphoto.com/5/0/4/large1500/405734930.jpg",
            "alt": ""
        },
        {
            "src": "https://img.freepik.com/free-photo/wrinkled-plastic-wrap-texture-black-background_53876-96738.jpg?size=626&ext=jpg",
            "alt": ""
        },
        {
            "src": "https://wallpaperaccess.com/full/5704566.jpg",
            "alt": ""
        }
        ]
        }
    },
    {
        "id": 8,
        "name": "Shape3",
        "category": "plastic", 
        "price": 10441,
        "currency": "USD",
        "image": "https://images.fineartamerica.com/images-medium-large-5/brushed-steel-metal-texture-2-redlightimage.jpg",
        "bestseller": false, 
        "featured": false,
        "details": null
    },
    {
        "id": 19,
        "name": "Shape2123",
        "category": "concrete", 
        "price": 156,
        "currency": "USD",
        "image": "https://images.fineartamerica.com/images-medium-large-5/brushed-steel-metal-texture-2-redlightimage.jpg",
        "bestseller": true, 
        "featured": false,
        "details": null
    },
    {
        "id": 112,
        "name": "Wave123",
        "category": "brick",
        "price": 120.21,
        "currency": "USD", 
        "image": {
        "src": "https://ae01.alicdn.com/kf/Haf859724a1fb4969b0c14c361feafa753/Plaque-en-acier-inoxydable-1-5-paisseur-de-1mm-304mm-2mm-3mm-traitement-du-m-tal.jpg_Q90.jpg_.webp",
        "alt": ""
        },
        "bestseller": false, 
        "featured": false,
        "details": null
    },
 
    {
        "id": 111,
        "name": "Shapedddd",
        "category": "wood",
        "price": 93.89,
        "currency": "USD",
        "image": {
            "src": "http://geomiq.com/wp-content/uploads/2019/08/kisspng-sheet-metal-molybdenum-stainless-steel-rolling-inc-steel-plate-5aea05f508ace2.0164818015252863890355.png"
        },
        "bestseller": false, 
        "featured": false,
        "details": null
    }
]
}